f1_2019_telemetry/packets.py
f1_2019_telemetry/cli/monitor.py
f1_2019_telemetry/cli/player.py
f1_2019_telemetry/cli/recorder.py
f1_2019_telemetry/cli/threading_utils.py
f1_2019_telemetry-1.1.4.dist-info/LICENSE
f1_2019_telemetry-1.1.4.dist-info/METADATA
f1_2019_telemetry-1.1.4.dist-info/WHEEL
f1_2019_telemetry-1.1.4.dist-info/entry_points.txt
f1_2019_telemetry-1.1.4.dist-info/top_level.txt
f1_2019_telemetry-1.1.4.dist-info/RECORD
