Metadata-Version: 2.1
Name: f1-2019-telemetry
Version: 1.1.4
Summary: A package to handle UDP telemetry data as sent by the F1 2019 game.
Home-page: https://pypi.org/project/f1-2019-telemetry/
Author: Sidney Cadot
Author-email: sidney@jigsaw.nl
License: UNKNOWN
Project-URL: Documentation, https://f1-2019-telemetry.readthedocs.io/en/latest/
Project-URL: Source Repository, https://gitlab.com/reddish/f1-2019-telemetry/
Platform: UNKNOWN
Classifier: Programming Language :: Python :: 3
Classifier: License :: OSI Approved :: MIT License
Classifier: Topic :: Games/Entertainment
Classifier: Operating System :: OS Independent
Requires-Python: >=3.6
